[
  {
    "title": "IVR QA Tester",
    "link": "https://jobs.techto.org/jobs/132062983-ivr-qa-tester",
    "company": "GuruLink",
    "jobType": "Full-time",
    "location": "",
    "postedDate": "4m ago",
    "tags": "Product & Engineering"
  },
  {
    "title": "Product Manager",
    "link": "https://jobs.techto.org/jobs/134198463-product-manager",
    "company": "GuruLink",
    "jobType": "Full-time",
    "location": "",
    "postedDate": "4m ago",
    "tags": "Product & Engineering"
  },
  {
    "title": "Head of Engineering",
    "link": "https://jobs.techto.org/jobs/135398526-head-of-engineering",
    "company": "GuruLink",
    "jobType": "Full-time",
    "location": "",
    "postedDate": "4m ago",
    "tags": "Product & Engineering"
  },
  {
    "title": "Technical Solution and Implementation Consultant",
    "link": "https://jobs.techto.org/jobs/134268618-technical-solution-and-implementation-consultant",
    "company": "SuiteSpot Technology",
    "jobType": "Full-time",
    "location": "Remote (Toronto, ON)",
    "postedDate": "2m ago",
    "tags": "Product & Engineering"
  },
  {
    "title": "Automotive Production Manager",
    "link": "https://jobs.techto.org/jobs/126075964-automotive-production-manager",
    "company": "Clutch Technologies Inc.",
    "jobType": "",
    "location": "",
    "postedDate": "3w ago",
    "tags": "Product & Engineering, TechTO Rocketships"
  },
  {
    "title": "Senior Product Manager",
    "link": "https://jobs.techto.org/jobs/160870790-senior-product-manager",
    "company": "Relay",
    "jobType": "Full-time",
    "location": "Remote (Toronto, Ontario, Canada)",
    "postedDate": "3w ago",
    "tags": "Product & Engineering, TechTO Rocketships"
  },
  {
    "title": "Senior Analytics Engineer",
    "link": "https://jobs.techto.org/jobs/162313944-senior-analytics-engineer",
    "company": "Clutch Technologies Inc.",
    "jobType": "",
    "location": "",
    "postedDate": "2w ago",
    "tags": "Product & Engineering, TechTO Rocketships"
  },
  {
    "title": "Forward Deployed Engineer, Infrastructure Specialist",
    "link": "https://jobs.techto.org/jobs/162407292-forward-deployed-engineer-infrastructure-specialist",
    "company": "Cohere",
    "jobType": "Full-time",
    "location": "Remote (Toronto, Ontario, Canada)",
    "postedDate": "2w ago",
    "tags": "Product & Engineering, TechTO Rocketships"
  },
  {
    "title": "Senior Java Developer, Capital Markets",
    "link": "https://jobs.techto.org/jobs/162350566-senior-java-developer-capital-markets",
    "company": "Alithya",
    "jobType": "Full-time",
    "location": "",
    "postedDate": "2w ago",
    "tags": "Product & Engineering, Java, capital market"
  },
  {
    "title": "Software Engineer",
    "link": "https://jobs.techto.org/jobs/162645878-software-engineer",
    "company": "Relay",
    "jobType": "Full-time",
    "location": "Remote (Toronto, Ontario, Canada)",
    "postedDate": "2w ago",
    "tags": "Product & Engineering, TechTO Rocketships"
  },
  {
    "title": "Senior Frontend Engineer",
    "link": "https://jobs.techto.org/jobs/162577538-senior-frontend-engineer",
    "company": "Ideogram",
    "jobType": "Full-time",
    "location": "",
    "postedDate": "2w ago",
    "tags": "Product & Engineering, TechTO Rocketships"
  },
  {
    "title": "Senior Software Engineer, Secure Agents",
    "link": "https://jobs.techto.org/jobs/134100540-senior-software-engineer-secure-agents",
    "company": "Cohere",
    "jobType": "Full-time",
    "location": "Remote (Toronto, Ontario, Canada)",
    "postedDate": "2w ago",
    "tags": "Product & Engineering, TechTO Rocketships"
  },
  {
    "title": "Senior Security Engineer (Purple Team)",
    "link": "https://jobs.techto.org/jobs/163429415-senior-security-engineer-purple-team",
    "company": "Relay",
    "jobType": "Full-time",
    "location": "Remote (Toronto, Ontario, Canada)",
    "postedDate": "1w ago",
    "tags": "Product & Engineering, TechTO Rocketships"
  },
  {
    "title": "Staff Product Manager",
    "link": "https://jobs.techto.org/jobs/164715434-staff-product-manager",
    "company": "Relay",
    "jobType": "Full-time",
    "location": "Remote (Toronto, Ontario, Canada)",
    "postedDate": "5d ago",
    "tags": "Product & Engineering, TechTO Rocketships"
  },
  {
    "title": "Technical Support Specialist",
    "link": "https://jobs.techto.org/jobs/164829437-technical-support-specialist",
    "company": "Certn",
    "jobType": "Full-time",
    "location": "Remote (Toronto, Ontario, Canada)",
    "postedDate": "4d ago",
    "tags": "Product & Engineering, TechTO Rocketships"
  },
  {
    "title": "Full Stack Developer",
    "link": "https://jobs.techto.org/jobs/164752259-full-stack-developer",
    "company": "Koru",
    "jobType": "Full-time",
    "location": "",
    "postedDate": "4d ago",
    "tags": "Product & Engineering, full-stack, engineering, developer"
  },
  {
    "title": "Senior Manager of Engineering",
    "link": "https://jobs.techto.org/jobs/165230661-senior-manager-of-engineering",
    "company": "Loopio Inc.",
    "jobType": "Full-time",
    "location": "Remote (Toronto, Ontario, Canada)",
    "postedDate": "22h ago",
    "tags": "Product & Engineering, TechTO Rocketships"
  },
  {
    "title": "Senior Cloud Engineer",
    "link": "https://jobs.techto.org/jobs/165230660-senior-cloud-engineer",
    "company": "Loopio Inc.",
    "jobType": "Full-time",
    "location": "Remote (Toronto, Ontario, Canada)",
    "postedDate": "22h ago",
    "tags": "Product & Engineering, TechTO Rocketships"
  }
]