[
  {
    "title": "Co-op or Intern, Data & Analytics (May 2026)",
    "link": "https://digitalnovascotia.com/job-posts/co-op-or-intern-data-analytics-may-2026/",
    "company": "BDO Canada LLP",
    "location": "Halifax",
    "jobType": "Co-op",
    "postedDate": "49 minutes ago"
  },
  {
    "title": "Co-op or Intern, DevOps Engineer (May 2026)",
    "link": "https://digitalnovascotia.com/job-posts/co-op-or-intern-devops-engineer-may-2026/",
    "company": "BDO Canada LLP",
    "location": "Halifax",
    "jobType": "Co-op",
    "postedDate": "52 minutes ago"
  },
  {
    "title": "Senior Workday Application Developer",
    "link": "https://digitalnovascotia.com/job-posts/senior-workday-application-developer/",
    "company": "BDO Canada LLP",
    "location": "Halifax",
    "jobType": "Full Time",
    "postedDate": "57 minutes ago"
  },
  {
    "title": "Senior Software Product Lead – German Combat Management System",
    "link": "https://digitalnovascotia.com/job-posts/senior-software-product-lead-german-combat-management-system/",
    "company": "Lockheed Martin Canada",
    "location": "Halifax",
    "jobType": "Full Time",
    "postedDate": "1 hour ago"
  },
  {
    "title": "Junior Software Engineer – Various Programs – Halifax",
    "link": "https://digitalnovascotia.com/job-posts/junior-software-engineer-various-programs/",
    "company": "Lockheed Martin Canada",
    "location": "Halifax",
    "jobType": "Full Time",
    "postedDate": "1 hour ago"
  },
  {
    "title": "Senior Software Engineer – Software Assurance Lead",
    "link": "https://digitalnovascotia.com/job-posts/senior-software-engineer-software-assurance-lead/",
    "company": "Lockheed Martin Canada",
    "location": "Halifax",
    "jobType": "Full Time",
    "postedDate": "1 hour ago"
  },
  {
    "title": "Senior Software Engineer – Agile Coach",
    "link": "https://digitalnovascotia.com/job-posts/senior-software-engineer-agile-coach-2/",
    "company": "Lockheed Martin Canada",
    "location": "Halifax",
    "jobType": "Full Time",
    "postedDate": "1 hour ago"
  },
  {
    "title": "DevSecOps Developer",
    "link": "https://digitalnovascotia.com/job-posts/devsecops-developer-2/",
    "company": "Lockheed Martin Canada",
    "location": "Halifax",
    "jobType": "Full Time",
    "postedDate": "1 hour ago"
  },
  {
    "title": "Client Technical Support Manager",
    "link": "https://digitalnovascotia.com/job-posts/3498716-2/",
    "company": "Venor Search Group",
    "location": "Halifax",
    "jobType": "Full Time",
    "postedDate": "3 hours ago"
  },
  {
    "title": "Project Manager",
    "link": "https://digitalnovascotia.com/job-posts/project-manager-69/",
    "company": "Meridia Recruitment Solutions & KBRS",
    "location": "Halifax",
    "jobType": "Full Time",
    "postedDate": "3 hours ago"
  },
  {
    "title": "Sr Director Enterprise Efficiency",
    "link": "https://digitalnovascotia.com/job-posts/sr-director-enterprise-efficiency/",
    "company": "Nova Scotia Power",
    "location": "Provincial",
    "jobType": "Full Time",
    "postedDate": "3 hours ago"
  },
  {
    "title": "Revenue Specialist",
    "link": "https://digitalnovascotia.com/job-posts/revenue-specialist/",
    "company": "Nova Scotia Power",
    "location": "Provincial",
    "jobType": "Full Time",
    "postedDate": "3 hours ago"
  },
  {
    "title": "Marketing Specialist",
    "link": "https://digitalnovascotia.com/job-posts/marketing-specialist-5/",
    "company": "Steele Auto Group",
    "location": "Halifax",
    "jobType": "Full Time",
    "postedDate": "22 hours ago"
  },
  {
    "title": "Creative Content Specialist",
    "link": "https://digitalnovascotia.com/job-posts/creative-content-specialist/",
    "company": "QEII Foundation",
    "location": "Halifax",
    "jobType": "Full Time",
    "postedDate": "22 hours ago"
  },
  {
    "title": "Application Support Engineer",
    "link": "https://digitalnovascotia.com/job-posts/application-support-engineer-4/",
    "company": "Nova Scotia Cyber Security & Digital Solutions (CSDS)",
    "location": "Halifax",
    "jobType": "Full Time",
    "postedDate": "1 day ago"
  },
  {
    "title": "Communications Specialist, Communications, Engagement and Change",
    "link": "https://digitalnovascotia.com/job-posts/3498689-2/",
    "company": "Nova Scotia Health & IWK",
    "location": "Pictou",
    "jobType": "Full Time",
    "postedDate": "1 day ago"
  },
  {
    "title": "Senior Application Developer",
    "link": "https://digitalnovascotia.com/job-posts/senior-application-developer/",
    "company": "Sobeys",
    "location": "Pictou",
    "jobType": "Full Time",
    "postedDate": "1 day ago"
  },
  {
    "title": "Senior Data Engineer – GFT Halifax",
    "link": "https://digitalnovascotia.com/job-posts/senior-data-engineer-gft-halifax-3/",
    "company": "RBC Technology & Operations",
    "location": "Halifax",
    "jobType": "Full Time",
    "postedDate": "1 day ago"
  },
  {
    "title": "Lead Engineer, Metadata Management – GFT – Halifax",
    "link": "https://digitalnovascotia.com/job-posts/lead-engineer-metadata-management-gft-halifax-4/",
    "company": "RBC Technology & Operations",
    "location": "Halifax",
    "jobType": "Full Time",
    "postedDate": "1 day ago"
  },
  {
    "title": "Lead Software Developer – GFT",
    "link": "https://digitalnovascotia.com/job-posts/lead-software-developer-gft-2/",
    "company": "RBC Technology & Operations",
    "location": "Halifax",
    "jobType": "Full Time",
    "postedDate": "1 day ago"
  },
  {
    "title": "Senior Software Developer (Python), GFT",
    "link": "https://digitalnovascotia.com/job-posts/senior-software-developer-python-gft/",
    "company": "RBC Technology & Operations",
    "location": "Halifax",
    "jobType": "Full Time",
    "postedDate": "1 day ago"
  },
  {
    "title": "Software Developer – GFT",
    "link": "https://digitalnovascotia.com/job-posts/software-developer-gft/",
    "company": "RBC Technology & Operations",
    "location": "Halifax",
    "jobType": "Full Time",
    "postedDate": "1 day ago"
  },
  {
    "title": "Power Platform Consultant",
    "link": "https://digitalnovascotia.com/job-posts/power-platform-consultant-4/",
    "company": "Mariner Partners Inc.",
    "location": "Halifax",
    "jobType": "Full Time",
    "postedDate": "2 days ago"
  },
  {
    "title": "Digital Marketing Technology Lead (9 Month Term)",
    "link": "https://digitalnovascotia.com/job-posts/digital-marketing-technology-lead-9-month-term-3/",
    "company": "CAA Atlantic",
    "location": "Halifax",
    "jobType": "Temporary",
    "postedDate": "2 days ago"
  },
  {
    "title": "Business Analyst, eHealth and Clinical Information Systems",
    "link": "https://digitalnovascotia.com/job-posts/business-analyst-ehealth-and-clinical-information-systems-4/",
    "company": "CGI Information Systems and Management Consultants Inc.",
    "location": "Halifax",
    "jobType": "Full Time",
    "postedDate": "2 days ago"
  },
  {
    "title": "Go-To-Market (GTM) Associate",
    "link": "https://digitalnovascotia.com/job-posts/go-to-market-gtm-associate/",
    "company": "REDspace Inc",
    "location": "Halifax",
    "jobType": "Full Time",
    "postedDate": "2 days ago"
  },
  {
    "title": "Senior Golang Developer (GCP and BigQuery )",
    "link": "https://digitalnovascotia.com/job-posts/senior-golang-developer-gcp-and-bigquery/",
    "company": "CGI Information Systems and Management Consultants Inc.",
    "location": "Halifax",
    "jobType": "Full Time",
    "postedDate": "2 days ago"
  },
  {
    "title": "Senior Software Developer",
    "link": "https://digitalnovascotia.com/job-posts/senior-software-developer-34/",
    "company": "CGI Information Systems and Management Consultants Inc.",
    "location": "Halifax",
    "jobType": "Full Time",
    "postedDate": "2 days ago"
  },
  {
    "title": "Dynatrace Architect",
    "link": "https://digitalnovascotia.com/job-posts/dynatrace-architect/",
    "company": "DXC Technology Canada",
    "location": "Halifax",
    "jobType": "Full Time",
    "postedDate": "2 days ago"
  },
  {
    "title": "Dynatrace Implementation Engineer",
    "link": "https://digitalnovascotia.com/job-posts/dynatrace-implementation-engineer/",
    "company": "DXC Technology Canada",
    "location": "Halifax",
    "jobType": "Full Time",
    "postedDate": "2 days ago"
  }
]